ematrix/__init__.py
ematrix/matrix.py
ematrix-0.0.9.dist-info/LICENSE.txt
ematrix-0.0.9.dist-info/METADATA
ematrix-0.0.9.dist-info/WHEEL
ematrix-0.0.9.dist-info/top_level.txt
ematrix-0.0.9.dist-info/RECORD
